dogemachine_utils/__init__.py
dogemachine_utils/aws_lambda_utils.py
dogemachine_utils/aws_login.py
dogemachine_utils/aws_s3_utils.py
dogemachine_utils/aws_sns_utils.py
dogemachine_utils/docker_utils.py
dogemachine_utils/file_utils.py
dogemachine_utils/log_formatting.py
dogemachine_utils/shell.py
dogemachine_utils/testing_utils.py
dogemachine_utils/text_parser_utils.py
dogemachine_utils/time_utils.py
dogemachine_utils/version.py
dogemachine_utils/zap_utils.py
DogeMachine_utils-0.2.1.dist-info/LICENSE
DogeMachine_utils-0.2.1.dist-info/METADATA
DogeMachine_utils-0.2.1.dist-info/WHEEL
DogeMachine_utils-0.2.1.dist-info/top_level.txt
DogeMachine_utils-0.2.1.dist-info/zip-safe
DogeMachine_utils-0.2.1.dist-info/RECORD
