Metadata-Version: 2.1
Name: DogeMachine-utils
Version: 0.2.1
Summary: UNKNOWN
Home-page: https://github.com/kmcquade/DogeMachine-utils
Author: Kinnaird McQuade
Author-email: kinnairdm@gmail.com
License: UNKNOWN
Keywords: security
Platform: UNKNOWN
Classifier: Programming Language :: Python :: 3
Classifier: License :: OSI Approved :: MIT License
Classifier: Operating System :: OS Independent
Requires-Python: >=3.8
Requires-Dist: botocore
Requires-Dist: boto3
Requires-Dist: PyYAML
